{"web":{"client_id":"22819640695-40ie511a43vdbh8p82o5uhm6b62529rm.apps.googleusercontent.com","project_id":"event-manager-1649890278206","auth_uri":"https://accounts.google.com/o/oauth2/auth","token_uri":"https://oauth2.googleapis.com/token","auth_provider_x509_cert_url":"https://www.googleapis.com/oauth2/v1/certs","client_secret":"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","redirect_uris":["https://eventmanagerzlf.herokuapp.com/api/v2/authentications","http://localhost/api/v2/authentications","http://localhost:8080/api/v2/authentications"],"javascript_origins":["https://eventmanagerzlf.herokuapp.com","http://localhost","http://localhost:8080"]}}